skeet.py
skeet-2.2.7.dist-info/entry_points.txt
skeet-2.2.7.dist-info/LICENSE
skeet-2.2.7.dist-info/WHEEL
skeet-2.2.7.dist-info/METADATA
skeet-2.2.7.dist-info/RECORD
