Metadata-Version: 2.3
Name: skeet
Version: 2.2.7
Summary: Describe what you want done in your terminal, and Skeet will use AI to make it happen.
Requires-Python: >=3.11
Requires-Dist: click>=8.1.8
Requires-Dist: promptic>=4.1.2
Requires-Dist: rich>=13.9.4
Requires-Dist: ruamel-yaml>=0.18.8
Project-URL: Source, https://github.com/knowsuchagency/skeet
